{
    "name": "a20",
    "start_without_cross": true,
    "steps": [
        {
            "label": "scan_right",
            "action": "RotateRight",
            "until": "line",
            "speed": 5,
            "strict_line": true
        },
        {
            "action": "AutoLine",
            "enabled": true
        },
        {
            "label": "scan_left",
            "action": "RotateLeft",
            "speed": 5,
            "until": "line",
            "strict_line": true
        },
        {
            "label": "scan_right",
            "action": "RotateRight",
            "speed": 5,
            "until": "line",
            "strict_line": true
        },
        {
            "label": "scan_right",
            "action": "RotateRight",
            "speed": 5,
            "until": "line",
            "strict_line": true
        },
        {
            "label": "scan_right",
            "action": "RotateRight",
            "speed": 5,
            "until": "line",
            "strict_line": true
        },
        {
            "label": "scan_right",
            "action": "RotateRight",
            "speed": 5,
            "until": "line",
            "strict_line": true
        },
        {
            "action": "AutoLine",
            "enabled": false
        },
        {
            "action": "Stop"
        }
    ],
    "end_state": "stop"
}
